src/autoresevaluator/dataset/tabledata/titanic/preprocessing.py
src/autoresevaluator/main.py
src/autoresevaluator/metrix/binary_classification.py
src/autoresevaluator/metrix/multiclass_classificatio.py
src/autoresevaluator/metrix/regression.py
src/autoresevaluator/train/cross_validation.py
src/autoresevaluator/train/model_template.py
src/autoresevaluator/train/optuna.py
src/autoresevaluator/utils/log_config.py
autores_evaluator-0.1.0.dist-info/LICENSE
autores_evaluator-0.1.0.dist-info/METADATA
autores_evaluator-0.1.0.dist-info/WHEEL
autores_evaluator-0.1.0.dist-info/RECORD
